{
  "uuid": "697ac204-9ac6-3996-9215-037ca08c1786",
  "starterPrompted": true,
  "starterLocked": false,
  "starterSelected": true,
  "starterUUID": "dd2d0c4b-32fa-4c1c-af9d-e0d877c70de7",
  "keyItems": [],
  "battleTheme": "cobblemon:battle.pvp.default",
  "extraData": {},
  "advancementData": {
    "totalCaptureCount": 0,
    "totalEggsCollected": 0,
    "totalEggsHatched": 0,
    "totalEvolvedCount": 0,
    "totalBattleVictoryCount": 3,
    "totalPvPBattleVictoryCount": 0,
    "totalPvWBattleVictoryCount": 3,
    "totalPvNBattleVictoryCount": 0,
    "totalShinyCaptureCount": 0,
    "totalTradedCount": 0,
    "totalTypeCaptureCounts": {},
    "totalDefeatedCounts": {
      "cobblemon:combee": 1,
      "cobblemon:vivillon": 1,
      "cobblemon:lechonk": 1
    },
    "aspectsCollected": {}
  }
}